mobidec_package_test/__init__.py
mobidec_package_test/main.py
mobidec_package_test/divider/__init__.py
mobidec_package_test/divider/divider.py
mobidec_package_test/divider/divider_error.py
mobidec_package_test-0.1.0.dist-info/METADATA
mobidec_package_test-0.1.0.dist-info/WHEEL
mobidec_package_test-0.1.0.dist-info/top_level.txt
mobidec_package_test-0.1.0.dist-info/RECORD
