Metadata-Version: 2.4
Name: mobidec_package_test
Version: 0.1.0
Summary: Adaptation of the template for github.
Maintainer-email: moulinba <baptiste.moulin.externe2@ifpen.fr>, kleinf <florian.klein@ifpen.fr>
License: MIT License
Classifier: Programming Language :: Python :: 3.12
Classifier: License :: OSI Approved :: MIT License
Classifier: Operating System :: OS Independent
Requires-Python: >=3.12
Requires-Dist: pytest==8.0.1
